pygohome/__init__.py
pygohome/convert.py
pygohome/jupygohome.py
pygohome/processor.py
pygohome/world.py
pygohome-0.2.1.dist-info/LICENSE
pygohome-0.2.1.dist-info/METADATA
pygohome-0.2.1.dist-info/WHEEL
pygohome-0.2.1.dist-info/top_level.txt
pygohome-0.2.1.dist-info/RECORD
