Metadata-Version: 2.1
Name: pygohome
Version: 0.2.1
Summary: A 100% personal route optimizer in a known environment based on experience.
Home-page: https://github.com/eumiro/pygohome/
Author: Miroslav Šedivý
Author-email: eumiro@gmail.com
Maintainer: Miroslav Šedivý
Maintainer-email: eumiro@gmail.com
License: BSD-3
Keywords: gps,navigation,routing,bicycle,walk,optimal route
Platform: UNKNOWN
Classifier: Development Status :: 4 - Beta
Classifier: Environment :: Web Environment
Classifier: Framework :: Jupyter
Classifier: Intended Audience :: End Users/Desktop
Classifier: Intended Audience :: Science/Research
Classifier: License :: OSI Approved :: BSD License
Classifier: Operating System :: OS Independent
Classifier: Programming Language :: Python
Classifier: Programming Language :: Python :: 3
Classifier: Programming Language :: Python :: 3 :: Only
Classifier: Programming Language :: Python :: 3.6
Classifier: Programming Language :: Python :: 3.7
Classifier: Programming Language :: Python :: 3.8
Classifier: Programming Language :: Python :: 3.9
Classifier: Topic :: Scientific/Engineering :: GIS
Requires-Dist: gpxpy (>=1.4.2)
Requires-Dist: ipyleaflet (>=0.13.3)
Requires-Dist: ipywidgets (>=7.5.1)
Requires-Dist: networkx (>=2.5)
Requires-Dist: notebook (>=6.1.5)
Requires-Dist: numpy (>=1.19.4)
Requires-Dist: pandas (>=1.1.5)
Requires-Dist: scipy (>=1.5.4)
Requires-Dist: utm (>=0.7.0)
Provides-Extra: test
Requires-Dist: pytest ; extra == 'test'
